{
    "colors": {
        "r": 78,
        "g": 75,
        "b": 66,
        "black": "#000000",
        "light_black": "#dad4bb",
        "grey": "rgba(180, 175, 154, 0.3)"
    },
    "cssvars": {
        "font_main": "United Sans Medium",
        "font_main_light": "United Sans Light"
    },
    "terminal": {
        "fontFamily": "Fira Mono",
        "cursorStyle": "block",
        "foreground": "#4e4b42",
        "background": "#dad4bb",
        "cursor": "#4e4b42",
        "cursorAccent": "#4e4b42",
        "selection": "rgba(240,238,233,0.3)"
    },
    "globe": {
        "base": "#000000",
        "marker": "#f0eee9",
        "pin": "#f0eee9",
        "satellite": "#f0eee9"
    },
    "injectCSS":"body:after{content:'';position:absolute;top:0;left:0;bottom:0;right:0;box-shadow:inset 0 0 25vw rgba(0,0,0,.5);pointer-events:none}body{background:var(--color_light_black);background-image:linear-gradient(rgb(180,175,154,.1) 2px,transparent .1em),linear-gradient(90deg,rgb(180,175,154 ,.1) 2px,transparent .1em);background-size:6px 6px} section#keyboard{width: 100vw;} div.keyboard_key{margin: 0vh 0.8vh;} div.keyboard_key#keyboard_spacebar{width: 53.5vh;min-width: 53.5vh;} section#filesystem{display:none;}"
}
